{"metadata": {"dbt_schema_version": "https://schemas.getdbt.com/dbt/run-results/v4.json", "dbt_version": "1.2.6", "generated_at": "2024-05-17T10:52:21.914851Z", "invocation_id": "480f9874-4951-4d79-9130-f8107ced3654", "env": {}}, "results": [{"status": "success", "timing": [{"name": "compile", "started_at": "2024-05-17T10:52:21.780937Z", "completed_at": "2024-05-17T10:52:21.784121Z"}, {"name": "execute", "started_at": "2024-05-17T10:52:21.784483Z", "completed_at": "2024-05-17T10:52:21.863190Z"}], "thread_id": "Thread-1", "execution_time": 0.08316564559936523, "adapter_response": {"_message": "SELECT 2", "code": "SELECT", "rows_affected": 2}, "message": "SELECT 2", "failures": null, "unique_id": "model.test1.my_first_dbt_model"}, {"status": "success", "timing": [{"name": "compile", "started_at": "2024-05-17T10:52:21.865985Z", "completed_at": "2024-05-17T10:52:21.868441Z"}, {"name": "execute", "started_at": "2024-05-17T10:52:21.868677Z", "completed_at": "2024-05-17T10:52:21.904976Z"}], "thread_id": "Thread-1", "execution_time": 0.039878129959106445, "adapter_response": {"_message": "CREATE VIEW", "code": "CREATE VIEW", "rows_affected": -1}, "message": "CREATE VIEW", "failures": null, "unique_id": "model.test1.my_second_dbt_model"}], "elapsed_time": 0.21639204025268555, "args": {"write_json": true, "use_colors": true, "printer_width": 80, "version_check": true, "partial_parse": true, "static_parser": true, "profiles_dir": "/home/spatika/.dbt", "send_anonymous_usage_stats": true, "event_buffer_size": 100000, "quiet": false, "no_print": false, "cache_selected_only": false, "which": "run", "rpc_method": "run", "indirect_selection": "eager"}}